nmdmail/__init__.py
nmdmail/api.py
nmdmail/cli.py
nmdmail/default.css
nmdmail/helpers.py
nmdmail/py.typed
nmdmail-0.5.0.dist-info/METADATA
nmdmail-0.5.0.dist-info/WHEEL
nmdmail-0.5.0.dist-info/licenses/LICENSE
nmdmail-0.5.0.dist-info/RECORD
