Metadata-Version: 2.4
Name: nmdmail
Version: 0.5.0
Summary: Send emails written in Markdown
Author-email: Guilhem Saurel <guilhem.saurel@laas.fr>, Jianye Ye <yejianye@gmail.com>
License-Expression: BSD-2-Clause
License-File: LICENSE
Keywords: email,html,inline css,markdown
Requires-Python: >=3.9
Requires-Dist: beautifulsoup4>=4.13.3
Requires-Dist: emails>=0.6
Requires-Dist: lxml>=5.3.1
Requires-Dist: markdown>=3.7
Requires-Dist: premailer>=3.10.0
